musictheorpy/__init__.py
musictheorpy/chords.py
musictheorpy/interval_utils.py
musictheorpy/notegroups.py
musictheorpy/notes.py
musictheorpy/scales.py
musictheorpy/tests/__init__.py
musictheorpy/tests/test_chords.py
musictheorpy/tests/test_note.py
musictheorpy/tests/test_scale.py
musictheorpy-1.3.1.dist-info/LICENSE
musictheorpy-1.3.1.dist-info/METADATA
musictheorpy-1.3.1.dist-info/WHEEL
musictheorpy-1.3.1.dist-info/top_level.txt
musictheorpy-1.3.1.dist-info/RECORD
