Metadata-Version: 2.1
Name: musictheorpy
Version: 1.3.1
Summary: A music theory library for Python
Home-page: https://github.com/Jeff-Moorhead/musictheorpy
Author: Jeffrey Moorhead
Author-email: jeff.moorhead1@gmail.com
License: UNKNOWN
Platform: UNKNOWN
Classifier: Programming Language :: Python :: 3
Classifier: License :: OSI Approved :: MIT License
Classifier: Operating System :: OS Independent
